LICENSE
MANIFEST.in
README.md
requirements.txt
setup.py
bin/nopassword
nopassword/__init__.py
nopassword/fs.py
nopassword/keyfile.py
nopassword/nopasslib.py
nopassword.egg-info/PKG-INFO
nopassword.egg-info/SOURCES.txt
nopassword.egg-info/dependency_links.txt
nopassword.egg-info/requires.txt
nopassword.egg-info/top_level.txt