Metadata-Version: 1.0
Name: nopassword
Version: 0.1.4
Summary: Determenistic password generator
Home-page: https://github.com/nopassword/nopassword.py
Author: oskarnyqvist
Author-email: oskarnyqvist@gmail.com
License:                                  Apache License
